fluxify/__init__.py
fluxify/exceptions.py
fluxify/lazy_mapper.py
fluxify/mapper.py
fluxify/utils.py
fluxify/handler/__init__.py
fluxify/handler/conditions.py
fluxify/handler/csv.py
fluxify/handler/json.py
fluxify/handler/xmlh.py
fluxify/helper/__init__.py
fluxify/helper/yamlparser.py
fluxify/transformers/__init__.py
fluxify/transformers/boolean.py
fluxify/transformers/custom.py
fluxify/transformers/date.py
fluxify/transformers/number.py
fluxify/transformers/replace.py
fluxify/transformers/split.py
fluxify/transformers/transformer.py
fluxify-0.0.14.dist-info/METADATA
fluxify-0.0.14.dist-info/WHEEL
fluxify-0.0.14.dist-info/top_level.txt
fluxify-0.0.14.dist-info/RECORD
