Metadata-Version: 2.1
Name: fluxify
Version: 0.0.14
Summary: A Python package that eases the process of retrieving, organizing and altering data.
Home-page: https://github.com/ibragim64/fluxify
Author: Ibragim Abubakarov
Author-email: ibragim.ai95@gmail.com
Maintainer: Ibragim Abubakarov
Maintainer-email: ibragim.ai95@gmail.com
License: UNKNOWN
Platform: UNKNOWN
Classifier: Programming Language :: Python :: 3
Classifier: Operating System :: OS Independent
Classifier: Intended Audience :: Developers
Requires-Dist: pandas
Requires-Dist: PyYAML
Requires-Dist: imperium
Requires-Dist: ijson
